README.md
setup.cfg
setup.py
blockchain_exploration/__init__.py
blockchain_exploration/currencies.py
blockchain_exploration/exploration.py
blockchain_exploration/types.py
blockchain_exploration.egg-info/PKG-INFO
blockchain_exploration.egg-info/SOURCES.txt
blockchain_exploration.egg-info/dependency_links.txt
blockchain_exploration.egg-info/top_level.txt
test/test_exploration.py